{
  "timestamp": "2025-04-19T09:08:56.966408",
  "portfolio_value": {
    "cash": 18612.05,
    "portfolio_value": 98834.05,
    "positions_value": 80222.0
  },
  "results": [
    {
      "symbol": "AAPL",
      "decision": "HOLD",
      "confidence": 0.5,
      "reason": "No ORB data available",
      "trade_executed": true,
      "message": "Queued HOLD for next market open",
      "queued": true,
      "timestamp": "2025-04-19T09:08:55.642529"
    },
    {
      "symbol": "MSFT",
      "decision": "HOLD",
      "confidence": 0.5,
      "reason": "No ORB data available",
      "trade_executed": true,
      "message": "Queued HOLD for next market open",
      "queued": true,
      "timestamp": "2025-04-19T09:08:55.777656"
    },
    {
      "symbol": "GOOGL",
      "decision": "HOLD",
      "confidence": 0.5,
      "reason": "No ORB data available",
      "trade_executed": true,
      "message": "Queued HOLD for next market open",
      "queued": true,
      "timestamp": "2025-04-19T09:08:55.934642"
    },
    {
      "symbol": "AMZN",
      "decision": "HOLD",
      "confidence": 0.5,
      "reason": "No ORB data available",
      "trade_executed": true,
      "message": "Queued HOLD for next market open",
      "queued": true,
      "timestamp": "2025-04-19T09:08:56.084288"
    },
    {
      "symbol": "META",
      "decision": "HOLD",
      "confidence": 0.5,
      "reason": "No ORB data available",
      "trade_executed": true,
      "message": "Queued HOLD for next market open",
      "queued": true,
      "timestamp": "2025-04-19T09:08:56.239354"
    },
    {
      "symbol": "TSLA",
      "decision": "HOLD",
      "confidence": 0.5,
      "reason": "No ORB data available",
      "trade_executed": true,
      "message": "Queued HOLD for next market open",
      "queued": true,
      "timestamp": "2025-04-19T09:08:56.384816"
    },
    {
      "symbol": "NVDA",
      "decision": "HOLD",
      "confidence": 0.5,
      "reason": "No ORB data available",
      "trade_executed": true,
      "message": "Queued HOLD for next market open",
      "queued": true,
      "timestamp": "2025-04-19T09:08:56.545219"
    },
    {
      "symbol": "AMD",
      "decision": "HOLD",
      "confidence": 0.5,
      "reason": "No ORB data available",
      "trade_executed": true,
      "message": "Queued HOLD for next market open",
      "queued": true,
      "timestamp": "2025-04-19T09:08:56.691450"
    },
    {
      "symbol": "INTC",
      "decision": "HOLD",
      "confidence": 0.5,
      "reason": "No ORB data available",
      "trade_executed": true,
      "message": "Queued HOLD for next market open",
      "queued": true,
      "timestamp": "2025-04-19T09:08:56.818509"
    },
    {
      "symbol": "IBM",
      "decision": "HOLD",
      "confidence": 0.5,
      "reason": "No ORB data available",
      "trade_executed": true,
      "message": "Queued HOLD for next market open",
      "queued": true,
      "timestamp": "2025-04-19T09:08:56.942763"
    }
  ]
}